pykostalpiko/__init__.py
pykostalpiko/__main__.py
pykostalpiko/dxs/__init__.py
pykostalpiko/dxs/current_values.py
pykostalpiko/dxs/entry.py
pykostalpiko/dxs/inverter.py
pykostalpiko/dxs/statistics.py
pykostalpiko-1.1.2.dist-info/LICENSE
pykostalpiko-1.1.2.dist-info/METADATA
pykostalpiko-1.1.2.dist-info/WHEEL
pykostalpiko-1.1.2.dist-info/top_level.txt
pykostalpiko-1.1.2.dist-info/RECORD
