Metadata-Version: 2.1
Name: pykostalpiko
Version: 1.1.2
Summary: A library and CLI-tool to fetch the data from a Kostal Piko inverter
Home-page: https://github.com/Florian7843/pykostalpiko
Author: Florian Schmidt
Author-email: floriansch7843@gmail.com
License: MIT
Classifier: License :: OSI Approved :: MIT License
Classifier: Programming Language :: Python
Classifier: Programming Language :: Python :: 3
Classifier: Programming Language :: Python :: 3.7
Classifier: Programming Language :: Python :: Implementation :: CPython
Classifier: Programming Language :: Python :: Implementation :: PyPy
Requires-Python: >=3.7.0
License-File: LICENSE
Requires-Dist: aiohttp
